{
  "generated_at": "2025-10-06T18:42:26.177144+00:00",
  "symbols": {
    "IXHL": {
      "summary": {
        "posts": 30,
        "bullish_score": 200.07,
        "bearish_score": 107.32,
        "net_score": 92.75,
        "bullish_posts": 20,
        "bearish_posts": 7,
        "neutral_posts": 3,
        "engagement_breakdown": {
          "high": 27,
          "medium": 2,
          "low": 1
        },
        "top_posts": [
          {
            "id": "ixhl_012",
            "author": "bul_IXHL_12",
            "created_at": "2025-08-12T13:00:00+00:00",
            "text": "Small add to $IXHL calls after that bullish conference note.",
            "url": "https://twitter.com/sample/ixhl/12",
            "weight": 23.76,
            "sentiment": "bullish",
            "like_count": 161,
            "repost_count": 74,
            "engagement_level": "high"
          },
          {
            "id": "ixhl_021",
            "author": "bea_IXHL_21",
            "created_at": "2025-08-12T13:45:00+00:00",
            "text": "$IXHL bearish engulfing candle—took profit and watching for puts.",
            "url": "https://twitter.com/sample/ixhl/21",
            "weight": -22.35,
            "sentiment": "bearish",
            "like_count": 245,
            "repost_count": 31,
            "engagement_level": "high"
          },
          {
            "id": "ixhl_027",
            "author": "bea_IXHL_27",
            "created_at": "2025-08-12T14:15:00+00:00",
            "text": "$IXHL short interest rising again, bears might be right.",
            "url": "https://twitter.com/sample/ixhl/27",
            "weight": -21.62,
            "sentiment": "bearish",
            "like_count": 323,
            "repost_count": 67,
            "engagement_level": "high"
          },
          {
            "id": "ixhl_024",
            "author": "bea_IXHL_24",
            "created_at": "2025-08-12T14:00:00+00:00",
            "text": "$IXHL selling pressure heavy, dump likely if $3 fails.",
            "url": "https://twitter.com/sample/ixhl/24",
            "weight": -18.26,
            "sentiment": "bearish",
            "like_count": 284,
            "repost_count": 49,
            "engagement_level": "high"
          },
          {
            "id": "ixhl_023",
            "author": "bea_IXHL_23",
            "created_at": "2025-08-12T13:55:00+00:00",
            "text": "$IXHL red on the day; feels like distribution, staying short.",
            "url": "https://twitter.com/sample/ixhl/23",
            "weight": -17.14,
            "sentiment": "bearish",
            "like_count": 271,
            "repost_count": 43,
            "engagement_level": "high"
          }
        ]
      },
      "posts": [
        {
          "id": "ixhl_001",
          "source": "x",
          "symbol": "IXHL",
          "author": "bul_IXHL_1",
          "url": "https://twitter.com/sample/ixhl/1",
          "created_at": "2025-08-12T12:05:00+00:00",
          "text": "$IXHL bulls still in control after holding green all morning.",
          "like_count": 18,
          "reply_count": 2,
          "repost_count": 8,
          "weight": 3.52,
          "engagement_level": "medium"
        },
        {
          "id": "ixhl_002",
          "source": "x",
          "symbol": "IXHL",
          "author": "bul_IXHL_2",
          "url": "https://twitter.com/sample/ixhl/2",
          "created_at": "2025-08-12T12:10:00+00:00",
          "text": "Adding to $IXHL long calls, bullish structure intact above 3.",
          "like_count": 31,
          "reply_count": 3,
          "repost_count": 14,
          "weight": 9.28,
          "engagement_level": "medium"
        },
        {
          "id": "ixhl_003",
          "source": "x",
          "symbol": "IXHL",
          "author": "bul_IXHL_3",
          "url": "https://twitter.com/sample/ixhl/3",
          "created_at": "2025-08-12T12:15:00+00:00",
          "text": "$IXHL moon mission continues, buy volume keeps stacking.",
          "like_count": 44,
          "reply_count": 4,
          "repost_count": 20,
          "weight": 5.76,
          "engagement_level": "high"
        },
        {
          "id": "ixhl_004",
          "source": "x",
          "symbol": "IXHL",
          "author": "bul_IXHL_4",
          "url": "https://twitter.com/sample/ixhl/4",
          "created_at": "2025-08-12T12:20:00+00:00",
          "text": "$IXHL breakout retest complete—staying long into afternoon.",
          "like_count": 57,
          "reply_count": 5,
          "repost_count": 26,
          "weight": 3.44,
          "engagement_level": "high"
        },
        {
          "id": "ixhl_005",
          "source": "x",
          "symbol": "IXHL",
          "author": "bul_IXHL_5",
          "url": "https://twitter.com/sample/ixhl/5",
          "created_at": "2025-08-12T12:25:00+00:00",
          "text": "Seeing dip buyers step in on $IXHL, staying green despite market red.",
          "like_count": 70,
          "reply_count": 6,
          "repost_count": 32,
          "weight": 4.0,
          "engagement_level": "high"
        },
        {
          "id": "ixhl_006",
          "source": "x",
          "symbol": "IXHL",
          "author": "bul_IXHL_6",
          "url": "https://twitter.com/sample/ixhl/6",
          "created_at": "2025-08-12T12:30:00+00:00",
          "text": "$IXHL call sweep just printed, bullish confirmation for me.",
          "like_count": 83,
          "reply_count": 7,
          "repost_count": 38,
          "weight": 13.68,
          "engagement_level": "high"
        },
        {
          "id": "ixhl_007",
          "source": "x",
          "symbol": "IXHL",
          "author": "bul_IXHL_7",
          "url": "https://twitter.com/sample/ixhl/7",
          "created_at": "2025-08-12T12:35:00+00:00",
          "text": "Picked up more $IXHL shares, the bull case keeps getting stronger.",
          "like_count": 96,
          "reply_count": 8,
          "repost_count": 44,
          "weight": 5.12,
          "engagement_level": "high"
        },
        {
          "id": "ixhl_008",
          "source": "x",
          "symbol": "IXHL",
          "author": "bul_IXHL_8",
          "url": "https://twitter.com/sample/ixhl/8",
          "created_at": "2025-08-12T12:40:00+00:00",
          "text": "$IXHL long thesis playing out; guidance comment was bullish.",
          "like_count": 109,
          "reply_count": 9,
          "repost_count": 50,
          "weight": 17.04,
          "engagement_level": "high"
        },
        {
          "id": "ixhl_009",
          "source": "x",
          "symbol": "IXHL",
          "author": "bul_IXHL_9",
          "url": "https://twitter.com/sample/ixhl/9",
          "created_at": "2025-08-12T12:45:00+00:00",
          "text": "$IXHL bulls pressing highs, expecting more upside into close.",
          "like_count": 122,
          "reply_count": 10,
          "repost_count": 56,
          "weight": 6.24,
          "engagement_level": "high"
        },
        {
          "id": "ixhl_010",
          "source": "x",
          "symbol": "IXHL",
          "author": "bul_IXHL_10",
          "url": "https://twitter.com/sample/ixhl/10",
          "created_at": "2025-08-12T12:50:00+00:00",
          "text": "$IXHL momentum still green, adding to long starter.",
          "like_count": 135,
          "reply_count": 11,
          "repost_count": 62,
          "weight": 13.6,
          "engagement_level": "high"
        },
        {
          "id": "ixhl_011",
          "source": "x",
          "symbol": "IXHL",
          "author": "bul_IXHL_11",
          "url": "https://twitter.com/sample/ixhl/11",
          "created_at": "2025-08-12T12:55:00+00:00",
          "text": "$IXHL buy wall showing up again, bull flag forming.",
          "like_count": 148,
          "reply_count": 12,
          "repost_count": 68,
          "weight": 14.72,
          "engagement_level": "high"
        },
        {
          "id": "ixhl_012",
          "source": "x",
          "symbol": "IXHL",
          "author": "bul_IXHL_12",
          "url": "https://twitter.com/sample/ixhl/12",
          "created_at": "2025-08-12T13:00:00+00:00",
          "text": "Small add to $IXHL calls after that bullish conference note.",
          "like_count": 161,
          "reply_count": 0,
          "repost_count": 74,
          "weight": 23.76,
          "engagement_level": "high"
        },
        {
          "id": "ixhl_013",
          "source": "x",
          "symbol": "IXHL",
          "author": "bul_IXHL_13",
          "url": "https://twitter.com/sample/ixhl/13",
          "created_at": "2025-08-12T13:05:00+00:00",
          "text": "$IXHL accumulation in dark pools screams long to me.",
          "like_count": 174,
          "reply_count": 1,
          "repost_count": 0,
          "weight": 4.48,
          "engagement_level": "high"
        },
        {
          "id": "ixhl_014",
          "source": "x",
          "symbol": "IXHL",
          "author": "bul_IXHL_14",
          "url": "https://twitter.com/sample/ixhl/14",
          "created_at": "2025-08-12T13:10:00+00:00",
          "text": "Bullish divergence on $IXHL RSI confirmed; I'm long.",
          "like_count": 187,
          "reply_count": 2,
          "repost_count": 6,
          "weight": 15.12,
          "engagement_level": "high"
        },
        {
          "id": "ixhl_015",
          "source": "x",
          "symbol": "IXHL",
          "author": "bul_IXHL_15",
          "url": "https://twitter.com/sample/ixhl/15",
          "created_at": "2025-08-12T13:15:00+00:00",
          "text": "$IXHL base building beautifully, leaning bull into next catalyst.",
          "like_count": 200,
          "reply_count": 3,
          "repost_count": 12,
          "weight": 5.6,
          "engagement_level": "high"
        },
        {
          "id": "ixhl_016",
          "source": "x",
          "symbol": "IXHL",
          "author": "bul_IXHL_16",
          "url": "https://twitter.com/sample/ixhl/16",
          "created_at": "2025-08-12T13:20:00+00:00",
          "text": "$IXHL order book stacked on the bid, bullish structure intact.",
          "like_count": 213,
          "reply_count": 4,
          "repost_count": 18,
          "weight": 12.32,
          "engagement_level": "high"
        },
        {
          "id": "ixhl_017",
          "source": "x",
          "symbol": "IXHL",
          "author": "bul_IXHL_17",
          "url": "https://twitter.com/sample/ixhl/17",
          "created_at": "2025-08-12T13:25:00+00:00",
          "text": "Long $IXHL into next week's catalyst—setup too good.",
          "like_count": 226,
          "reply_count": 5,
          "repost_count": 24,
          "weight": 6.72,
          "engagement_level": "high"
        },
        {
          "id": "ixhl_018",
          "source": "x",
          "symbol": "IXHL",
          "author": "bul_IXHL_18",
          "url": "https://twitter.com/sample/ixhl/18",
          "created_at": "2025-08-12T13:30:00+00:00",
          "text": "$IXHL short interest collapsing; bulls clearly winning.",
          "like_count": 239,
          "reply_count": 6,
          "repost_count": 30,
          "weight": 0.0,
          "engagement_level": "high"
        },
        {
          "id": "ixhl_019",
          "source": "x",
          "symbol": "IXHL",
          "author": "bul_IXHL_19",
          "url": "https://twitter.com/sample/ixhl/19",
          "created_at": "2025-08-12T13:35:00+00:00",
          "text": "Another green close likely for $IXHL—staying long.",
          "like_count": 252,
          "reply_count": 7,
          "repost_count": 36,
          "weight": 15.68,
          "engagement_level": "high"
        },
        {
          "id": "ixhl_020",
          "source": "x",
          "symbol": "IXHL",
          "author": "bul_IXHL_20",
          "url": "https://twitter.com/sample/ixhl/20",
          "created_at": "2025-08-12T13:40:00+00:00",
          "text": "$IXHL tape strong, buyers defending every dip.",
          "like_count": 265,
          "reply_count": 8,
          "repost_count": 42,
          "weight": 8.4,
          "engagement_level": "high"
        },
        {
          "id": "ixhl_021",
          "source": "x",
          "symbol": "IXHL",
          "author": "bea_IXHL_21",
          "url": "https://twitter.com/sample/ixhl/21",
          "created_at": "2025-08-12T13:45:00+00:00",
          "text": "$IXHL bearish engulfing candle—took profit and watching for puts.",
          "like_count": 245,
          "reply_count": 10,
          "repost_count": 31,
          "weight": -22.35,
          "engagement_level": "high"
        },
        {
          "id": "ixhl_022",
          "source": "x",
          "symbol": "IXHL",
          "author": "bea_IXHL_22",
          "url": "https://twitter.com/sample/ixhl/22",
          "created_at": "2025-08-12T13:50:00+00:00",
          "text": "Shorting $IXHL pops until they prove margin expansion.",
          "like_count": 258,
          "reply_count": 11,
          "repost_count": 37,
          "weight": -8.01,
          "engagement_level": "high"
        },
        {
          "id": "ixhl_023",
          "source": "x",
          "symbol": "IXHL",
          "author": "bea_IXHL_23",
          "url": "https://twitter.com/sample/ixhl/23",
          "created_at": "2025-08-12T13:55:00+00:00",
          "text": "$IXHL red on the day; feels like distribution, staying short.",
          "like_count": 271,
          "reply_count": 12,
          "repost_count": 43,
          "weight": -17.14,
          "engagement_level": "high"
        },
        {
          "id": "ixhl_024",
          "source": "x",
          "symbol": "IXHL",
          "author": "bea_IXHL_24",
          "url": "https://twitter.com/sample/ixhl/24",
          "created_at": "2025-08-12T14:00:00+00:00",
          "text": "$IXHL selling pressure heavy, dump likely if $3 fails.",
          "like_count": 284,
          "reply_count": 0,
          "repost_count": 49,
          "weight": -18.26,
          "engagement_level": "high"
        },
        {
          "id": "ixhl_025",
          "source": "x",
          "symbol": "IXHL",
          "author": "bea_IXHL_25",
          "url": "https://twitter.com/sample/ixhl/25",
          "created_at": "2025-08-12T14:05:00+00:00",
          "text": "$IXHL bear case back on if they miss enrollment targets.",
          "like_count": 297,
          "reply_count": 1,
          "repost_count": 55,
          "weight": -9.69,
          "engagement_level": "high"
        },
        {
          "id": "ixhl_026",
          "source": "x",
          "symbol": "IXHL",
          "author": "bea_IXHL_26",
          "url": "https://twitter.com/sample/ixhl/26",
          "created_at": "2025-08-12T14:10:00+00:00",
          "text": "Opened $IXHL put spread, expect another leg down.",
          "like_count": 310,
          "reply_count": 2,
          "repost_count": 61,
          "weight": -10.25,
          "engagement_level": "high"
        },
        {
          "id": "ixhl_027",
          "source": "x",
          "symbol": "IXHL",
          "author": "bea_IXHL_27",
          "url": "https://twitter.com/sample/ixhl/27",
          "created_at": "2025-08-12T14:15:00+00:00",
          "text": "$IXHL short interest rising again, bears might be right.",
          "like_count": 323,
          "reply_count": 3,
          "repost_count": 67,
          "weight": -21.62,
          "engagement_level": "high"
        },
        {
          "id": "ixhl_028",
          "source": "x",
          "symbol": "IXHL",
          "author": "neu_IXHL_28",
          "url": "https://twitter.com/sample/ixhl/28",
          "created_at": "2025-08-12T14:20:00+00:00",
          "text": "$IXHL consolidating near VWAP; waiting for direction.",
          "like_count": 329,
          "reply_count": 5,
          "repost_count": 69,
          "weight": 0.0,
          "engagement_level": "high"
        },
        {
          "id": "ixhl_029",
          "source": "x",
          "symbol": "IXHL",
          "author": "neu_IXHL_29",
          "url": "https://twitter.com/sample/ixhl/29",
          "created_at": "2025-08-12T14:25:00+00:00",
          "text": "Listening to $IXHL investor call—mostly reiterating prior guidance.",
          "like_count": 342,
          "reply_count": 6,
          "repost_count": 75,
          "weight": 11.59,
          "engagement_level": "high"
        },
        {
          "id": "ixhl_030",
          "source": "x",
          "symbol": "IXHL",
          "author": "neu_IXHL_30",
          "url": "https://twitter.com/sample/ixhl/30",
          "created_at": "2025-08-12T14:30:00+00:00",
          "text": "Volume on $IXHL average so far; no clear read yet.",
          "like_count": 5,
          "reply_count": 7,
          "repost_count": 1,
          "weight": 0.0,
          "engagement_level": "low"
        }
      ],
      "history": [
        {
          "timestamp": "2025-10-03T23:45:24.793845",
          "net_score": 97.88,
          "bullish_score": 192.94,
          "bearish_score": 94.66,
          "posts": 32,
          "change_pct": 0.64,
          "close": 19.45,
          "volume": 820512.32
        },
        {
          "timestamp": "2025-10-04T00:45:24.793845",
          "net_score": 85.86,
          "bullish_score": 213.31,
          "bearish_score": 107.5,
          "posts": 33,
          "change_pct": 0.84,
          "close": 21.2,
          "volume": 1278508.76
        },
        {
          "timestamp": "2025-10-04T01:45:24.793845",
          "net_score": 105.3,
          "bullish_score": 207.71,
          "bearish_score": 105.52,
          "posts": 30,
          "change_pct": -0.57,
          "close": 18.13,
          "volume": 816446.99
        },
        {
          "timestamp": "2025-10-04T02:45:24.793845",
          "net_score": 91.98,
          "bullish_score": 192.24,
          "bearish_score": 100.89,
          "posts": 35,
          "change_pct": 0.54,
          "close": 21.57,
          "volume": 848194.97
        },
        {
          "timestamp": "2025-10-04T03:45:24.793845",
          "net_score": 103.43,
          "bullish_score": 197.89,
          "bearish_score": 105.92,
          "posts": 35,
          "change_pct": 1.25,
          "close": 20.91,
          "volume": 1057630.15
        },
        {
          "timestamp": "2025-10-04T04:45:24.793845",
          "net_score": 90.38,
          "bullish_score": 210.92,
          "bearish_score": 116.87,
          "posts": 32,
          "change_pct": 1.02,
          "close": 19.89,
          "volume": 814823.69
        },
        {
          "timestamp": "2025-10-04T05:45:24.793845",
          "net_score": 102.64,
          "bullish_score": 194.87,
          "bearish_score": 92.32,
          "posts": 31,
          "change_pct": -0.48,
          "close": 18.36,
          "volume": 932200.43
        },
        {
          "timestamp": "2025-10-04T06:45:24.793845",
          "net_score": 93.22,
          "bullish_score": 193.58,
          "bearish_score": 103.49,
          "posts": 30,
          "change_pct": 1.61,
          "close": 19.73,
          "volume": 1223095.45
        },
        {
          "timestamp": "2025-10-04T07:45:24.793845",
          "net_score": 108.11,
          "bullish_score": 204.56,
          "bearish_score": 104.34,
          "posts": 25,
          "change_pct": 0.12,
          "close": 20.69,
          "volume": 1293882.42
        },
        {
          "timestamp": "2025-10-04T08:45:24.793845",
          "net_score": 92.84,
          "bullish_score": 214.6,
          "bearish_score": 115.15,
          "posts": 34,
          "change_pct": 0.05,
          "close": 19.98,
          "volume": 1109122.81
        },
        {
          "timestamp": "2025-10-04T09:45:24.793845",
          "net_score": 112.56,
          "bullish_score": 203.02,
          "bearish_score": 119.9,
          "posts": 28,
          "change_pct": 0.17,
          "close": 20.8,
          "volume": 957859.13
        },
        {
          "timestamp": "2025-10-04T10:45:24.793845",
          "net_score": 74.98,
          "bullish_score": 198.54,
          "bearish_score": 105.69,
          "posts": 29,
          "change_pct": 0.78,
          "close": 18.11,
          "volume": 877577.5
        },
        {
          "timestamp": "2025-10-04T11:45:24.793845",
          "net_score": 90.36,
          "bullish_score": 195.02,
          "bearish_score": 103.94,
          "posts": 36,
          "change_pct": 0.83,
          "close": 20.28,
          "volume": 873470.53
        },
        {
          "timestamp": "2025-10-04T12:45:24.793845",
          "net_score": 110.44,
          "bullish_score": 192.67,
          "bearish_score": 106.78,
          "posts": 30,
          "change_pct": -2.25,
          "close": 20.97,
          "volume": 707763.13
        },
        {
          "timestamp": "2025-10-04T13:45:24.793845",
          "net_score": 77.84,
          "bullish_score": 208.22,
          "bearish_score": 92.78,
          "posts": 26,
          "change_pct": 2.27,
          "close": 19.36,
          "volume": 1150010.88
        },
        {
          "timestamp": "2025-10-04T14:45:24.793845",
          "net_score": 103.17,
          "bullish_score": 203.71,
          "bearish_score": 114.67,
          "posts": 33,
          "change_pct": 1.52,
          "close": 19.63,
          "volume": 1161078.74
        },
        {
          "timestamp": "2025-10-04T15:45:24.793845",
          "net_score": 79.58,
          "bullish_score": 207.68,
          "bearish_score": 115.66,
          "posts": 26,
          "change_pct": 0.5,
          "close": 18.93,
          "volume": 1250572.64
        },
        {
          "timestamp": "2025-10-04T16:45:24.793845",
          "net_score": 85.19,
          "bullish_score": 214.99,
          "bearish_score": 92.96,
          "posts": 35,
          "change_pct": -2.34,
          "close": 21.8,
          "volume": 1142736.5
        },
        {
          "timestamp": "2025-10-04T17:45:24.793845",
          "net_score": 85.4,
          "bullish_score": 193.3,
          "bearish_score": 100.92,
          "posts": 27,
          "change_pct": -1.44,
          "close": 20.8,
          "volume": 786043.93
        },
        {
          "timestamp": "2025-10-04T18:45:24.793845",
          "net_score": 105.62,
          "bullish_score": 214.09,
          "bearish_score": 109.53,
          "posts": 29,
          "change_pct": -1.39,
          "close": 18.28,
          "volume": 1031229.89
        },
        {
          "timestamp": "2025-10-04T19:45:24.793845",
          "net_score": 88.65,
          "bullish_score": 201.37,
          "bearish_score": 111.81,
          "posts": 26,
          "change_pct": 1.56,
          "close": 18.86,
          "volume": 721186.87
        },
        {
          "timestamp": "2025-10-04T20:45:24.793845",
          "net_score": 91.9,
          "bullish_score": 212.56,
          "bearish_score": 103.89,
          "posts": 28,
          "change_pct": -1.54,
          "close": 21.46,
          "volume": 957525.86
        },
        {
          "timestamp": "2025-10-04T21:45:24.793845",
          "net_score": 80.17,
          "bullish_score": 213.42,
          "bearish_score": 104.55,
          "posts": 24,
          "change_pct": 0.73,
          "close": 21.28,
          "volume": 764913.13
        },
        {
          "timestamp": "2025-10-04T22:45:24.793845",
          "net_score": 74.8,
          "bullish_score": 208.81,
          "bearish_score": 108.38,
          "posts": 32,
          "change_pct": 0.6,
          "close": 20.06,
          "volume": 737425.25
        },
        {
          "timestamp": "2025-10-04T23:55:31.516642+00:00",
          "net_score": 92.75,
          "bullish_score": 200.07,
          "bearish_score": 107.32,
          "posts": 30,
          "change_pct": null,
          "close": null,
          "volume": null
        },
        {
          "timestamp": "2025-10-06T18:42:26.177144+00:00",
          "net_score": 92.75,
          "bullish_score": 200.07,
          "bearish_score": 107.32,
          "posts": 30,
          "change_pct": null,
          "close": null,
          "volume": null
        }
      ],
      "price": {}
    },
    "AAPL": {
      "summary": {
        "posts": 30,
        "bullish_score": 151.71,
        "bearish_score": 86.94,
        "net_score": 64.77,
        "bullish_posts": 18,
        "bearish_posts": 6,
        "neutral_posts": 6,
        "engagement_breakdown": {
          "high": 27,
          "medium": 2,
          "low": 1
        },
        "top_posts": [
          {
            "id": "aapl_026",
            "author": "bea_AAPL_26",
            "created_at": "2025-08-11T22:10:00+00:00",
            "text": "Selling $AAPL strength ahead of earnings—bearish skew.",
            "url": "https://twitter.com/sample/aapl/26",
            "weight": -31.29,
            "sentiment": "bearish",
            "like_count": 314,
            "repost_count": 63,
            "engagement_level": "high"
          },
          {
            "id": "aapl_023",
            "author": "bea_AAPL_23",
            "created_at": "2025-08-11T21:55:00+00:00",
            "text": "Bearish note out of a major broker on $AAPL margins.",
            "url": "https://twitter.com/sample/aapl/23",
            "weight": -17.5,
            "sentiment": "bearish",
            "like_count": 275,
            "repost_count": 45,
            "engagement_level": "high"
          },
          {
            "id": "aapl_012",
            "author": "bul_AAPL_12",
            "created_at": "2025-08-11T21:00:00+00:00",
            "text": "Spike in $AAPL green volume this morning—longs in control.",
            "url": "https://twitter.com/sample/aapl/12",
            "weight": 15.84,
            "sentiment": "bullish",
            "like_count": 161,
            "repost_count": 74,
            "engagement_level": "high"
          },
          {
            "id": "aapl_007",
            "author": "bul_AAPL_7",
            "created_at": "2025-08-11T20:35:00+00:00",
            "text": "Apple Pay metrics bullish; staying long $AAPL.",
            "url": "https://twitter.com/sample/aapl/7",
            "weight": 15.36,
            "sentiment": "bullish",
            "like_count": 96,
            "repost_count": 44,
            "engagement_level": "high"
          },
          {
            "id": "aapl_011",
            "author": "bul_AAPL_11",
            "created_at": "2025-08-11T20:55:00+00:00",
            "text": "$AAPL cloud and AI talk has me bullish on multiple expansion.",
            "url": "https://twitter.com/sample/aapl/11",
            "weight": 14.72,
            "sentiment": "bullish",
            "like_count": 148,
            "repost_count": 68,
            "engagement_level": "high"
          }
        ]
      },
      "posts": [
        {
          "id": "aapl_001",
          "source": "x",
          "symbol": "AAPL",
          "author": "bul_AAPL_1",
          "url": "https://twitter.com/sample/aapl/1",
          "created_at": "2025-08-11T20:05:00+00:00",
          "text": "$AAPL buybacks plus services growth keep me bullish long term.",
          "like_count": 18,
          "reply_count": 2,
          "repost_count": 8,
          "weight": 7.04,
          "engagement_level": "medium"
        },
        {
          "id": "aapl_002",
          "source": "x",
          "symbol": "AAPL",
          "author": "bul_AAPL_2",
          "url": "https://twitter.com/sample/aapl/2",
          "created_at": "2025-08-11T20:10:00+00:00",
          "text": "$AAPL call buyers stepping in at the 240 strike—moon mode?",
          "like_count": 31,
          "reply_count": 3,
          "repost_count": 14,
          "weight": 6.96,
          "engagement_level": "medium"
        },
        {
          "id": "aapl_003",
          "source": "x",
          "symbol": "AAPL",
          "author": "bul_AAPL_3",
          "url": "https://twitter.com/sample/aapl/3",
          "created_at": "2025-08-11T20:15:00+00:00",
          "text": "Holding $AAPL long into product cycle; fundamentals still green.",
          "like_count": 44,
          "reply_count": 4,
          "repost_count": 20,
          "weight": 5.76,
          "engagement_level": "high"
        },
        {
          "id": "aapl_004",
          "source": "x",
          "symbol": "AAPL",
          "author": "bul_AAPL_4",
          "url": "https://twitter.com/sample/aapl/4",
          "created_at": "2025-08-11T20:20:00+00:00",
          "text": "$AAPL bulls happy with latest supply chain checks.",
          "like_count": 57,
          "reply_count": 5,
          "repost_count": 26,
          "weight": 3.44,
          "engagement_level": "high"
        },
        {
          "id": "aapl_005",
          "source": "x",
          "symbol": "AAPL",
          "author": "bul_AAPL_5",
          "url": "https://twitter.com/sample/aapl/5",
          "created_at": "2025-08-11T20:25:00+00:00",
          "text": "$AAPL guidance conservative, but I'm buying the dip.",
          "like_count": 70,
          "reply_count": 6,
          "repost_count": 32,
          "weight": 4.0,
          "engagement_level": "high"
        },
        {
          "id": "aapl_006",
          "source": "x",
          "symbol": "AAPL",
          "author": "bul_AAPL_6",
          "url": "https://twitter.com/sample/aapl/6",
          "created_at": "2025-08-11T20:30:00+00:00",
          "text": "$AAPL long from 238 working nicely, letting it ride.",
          "like_count": 83,
          "reply_count": 7,
          "repost_count": 38,
          "weight": 4.56,
          "engagement_level": "high"
        },
        {
          "id": "aapl_007",
          "source": "x",
          "symbol": "AAPL",
          "author": "bul_AAPL_7",
          "url": "https://twitter.com/sample/aapl/7",
          "created_at": "2025-08-11T20:35:00+00:00",
          "text": "Apple Pay metrics bullish; staying long $AAPL.",
          "like_count": 96,
          "reply_count": 8,
          "repost_count": 44,
          "weight": 15.36,
          "engagement_level": "high"
        },
        {
          "id": "aapl_008",
          "source": "x",
          "symbol": "AAPL",
          "author": "bul_AAPL_8",
          "url": "https://twitter.com/sample/aapl/8",
          "created_at": "2025-08-11T20:40:00+00:00",
          "text": "$AAPL wearables segment smashing expectations—bull case intact.",
          "like_count": 109,
          "reply_count": 9,
          "repost_count": 50,
          "weight": 5.68,
          "engagement_level": "high"
        },
        {
          "id": "aapl_009",
          "source": "x",
          "symbol": "AAPL",
          "author": "bul_AAPL_9",
          "url": "https://twitter.com/sample/aapl/9",
          "created_at": "2025-08-11T20:45:00+00:00",
          "text": "$AAPL keeps printing higher lows, still in buy mode.",
          "like_count": 122,
          "reply_count": 10,
          "repost_count": 56,
          "weight": 6.24,
          "engagement_level": "high"
        },
        {
          "id": "aapl_010",
          "source": "x",
          "symbol": "AAPL",
          "author": "bul_AAPL_10",
          "url": "https://twitter.com/sample/aapl/10",
          "created_at": "2025-08-11T20:50:00+00:00",
          "text": "Loaded a few $AAPL calls—momentum back in bull territory.",
          "like_count": 135,
          "reply_count": 11,
          "repost_count": 62,
          "weight": 13.6,
          "engagement_level": "high"
        },
        {
          "id": "aapl_011",
          "source": "x",
          "symbol": "AAPL",
          "author": "bul_AAPL_11",
          "url": "https://twitter.com/sample/aapl/11",
          "created_at": "2025-08-11T20:55:00+00:00",
          "text": "$AAPL cloud and AI talk has me bullish on multiple expansion.",
          "like_count": 148,
          "reply_count": 12,
          "repost_count": 68,
          "weight": 14.72,
          "engagement_level": "high"
        },
        {
          "id": "aapl_012",
          "source": "x",
          "symbol": "AAPL",
          "author": "bul_AAPL_12",
          "url": "https://twitter.com/sample/aapl/12",
          "created_at": "2025-08-11T21:00:00+00:00",
          "text": "Spike in $AAPL green volume this morning—longs in control.",
          "like_count": 161,
          "reply_count": 0,
          "repost_count": 74,
          "weight": 15.84,
          "engagement_level": "high"
        },
        {
          "id": "aapl_013",
          "source": "x",
          "symbol": "AAPL",
          "author": "bul_AAPL_13",
          "url": "https://twitter.com/sample/aapl/13",
          "created_at": "2025-08-11T21:05:00+00:00",
          "text": "$AAPL services mix trending up, still a buy IMO.",
          "like_count": 174,
          "reply_count": 1,
          "repost_count": 0,
          "weight": 4.48,
          "engagement_level": "high"
        },
        {
          "id": "aapl_014",
          "source": "x",
          "symbol": "AAPL",
          "author": "bul_AAPL_14",
          "url": "https://twitter.com/sample/aapl/14",
          "created_at": "2025-08-11T21:10:00+00:00",
          "text": "$AAPL long-term chart screaming bull continuation.",
          "like_count": 187,
          "reply_count": 2,
          "repost_count": 6,
          "weight": 10.08,
          "engagement_level": "high"
        },
        {
          "id": "aapl_015",
          "source": "x",
          "symbol": "AAPL",
          "author": "bul_AAPL_15",
          "url": "https://twitter.com/sample/aapl/15",
          "created_at": "2025-08-11T21:15:00+00:00",
          "text": "Institutional flows piling into $AAPL, bullish confirmation.",
          "like_count": 200,
          "reply_count": 3,
          "repost_count": 12,
          "weight": 11.2,
          "engagement_level": "high"
        },
        {
          "id": "aapl_016",
          "source": "x",
          "symbol": "AAPL",
          "author": "bul_AAPL_16",
          "url": "https://twitter.com/sample/aapl/16",
          "created_at": "2025-08-11T21:20:00+00:00",
          "text": "$AAPL China data better than feared—bullish update.",
          "like_count": 213,
          "reply_count": 4,
          "repost_count": 18,
          "weight": 6.16,
          "engagement_level": "high"
        },
        {
          "id": "aapl_017",
          "source": "x",
          "symbol": "AAPL",
          "author": "bul_AAPL_17",
          "url": "https://twitter.com/sample/aapl/17",
          "created_at": "2025-08-11T21:25:00+00:00",
          "text": "$AAPL hitting new highs—still room to run IMO.",
          "like_count": 226,
          "reply_count": 5,
          "repost_count": 24,
          "weight": 0.0,
          "engagement_level": "high"
        },
        {
          "id": "aapl_018",
          "source": "x",
          "symbol": "AAPL",
          "author": "bul_AAPL_18",
          "url": "https://twitter.com/sample/aapl/18",
          "created_at": "2025-08-11T21:30:00+00:00",
          "text": "Staying long $AAPL into next event—momentum strong.",
          "like_count": 239,
          "reply_count": 6,
          "repost_count": 30,
          "weight": 7.28,
          "engagement_level": "high"
        },
        {
          "id": "aapl_019",
          "source": "x",
          "symbol": "AAPL",
          "author": "bea_AAPL_19",
          "url": "https://twitter.com/sample/aapl/19",
          "created_at": "2025-08-11T21:35:00+00:00",
          "text": "$AAPL sell programs hitting; I trimmed my position.",
          "like_count": 223,
          "reply_count": 8,
          "repost_count": 21,
          "weight": -6.51,
          "engagement_level": "high"
        },
        {
          "id": "aapl_020",
          "source": "x",
          "symbol": "AAPL",
          "author": "bea_AAPL_20",
          "url": "https://twitter.com/sample/aapl/20",
          "created_at": "2025-08-11T21:40:00+00:00",
          "text": "$AAPL options flow leaning bearish this week.",
          "like_count": 236,
          "reply_count": 9,
          "repost_count": 27,
          "weight": -14.14,
          "engagement_level": "high"
        },
        {
          "id": "aapl_021",
          "source": "x",
          "symbol": "AAPL",
          "author": "bea_AAPL_21",
          "url": "https://twitter.com/sample/aapl/21",
          "created_at": "2025-08-11T21:45:00+00:00",
          "text": "Short $AAPL here—expect mean reversion after that rally.",
          "like_count": 249,
          "reply_count": 10,
          "repost_count": 33,
          "weight": -7.63,
          "engagement_level": "high"
        },
        {
          "id": "aapl_022",
          "source": "x",
          "symbol": "AAPL",
          "author": "bea_AAPL_22",
          "url": "https://twitter.com/sample/aapl/22",
          "created_at": "2025-08-11T21:50:00+00:00",
          "text": "$AAPL red alongside yields spiking—staying cautious.",
          "like_count": 262,
          "reply_count": 11,
          "repost_count": 39,
          "weight": 0.0,
          "engagement_level": "high"
        },
        {
          "id": "aapl_023",
          "source": "x",
          "symbol": "AAPL",
          "author": "bea_AAPL_23",
          "url": "https://twitter.com/sample/aapl/23",
          "created_at": "2025-08-11T21:55:00+00:00",
          "text": "Bearish note out of a major broker on $AAPL margins.",
          "like_count": 275,
          "reply_count": 12,
          "repost_count": 45,
          "weight": -17.5,
          "engagement_level": "high"
        },
        {
          "id": "aapl_024",
          "source": "x",
          "symbol": "AAPL",
          "author": "bea_AAPL_24",
          "url": "https://twitter.com/sample/aapl/24",
          "created_at": "2025-08-11T22:00:00+00:00",
          "text": "$AAPL put buyers active; I'm hedging long exposure.",
          "like_count": 288,
          "reply_count": 0,
          "repost_count": 51,
          "weight": 9.31,
          "engagement_level": "high"
        },
        {
          "id": "aapl_025",
          "source": "x",
          "symbol": "AAPL",
          "author": "bea_AAPL_25",
          "url": "https://twitter.com/sample/aapl/25",
          "created_at": "2025-08-11T22:05:00+00:00",
          "text": "$AAPL short thesis alive while hardware growth slows.",
          "like_count": 301,
          "reply_count": 1,
          "repost_count": 57,
          "weight": -9.87,
          "engagement_level": "high"
        },
        {
          "id": "aapl_026",
          "source": "x",
          "symbol": "AAPL",
          "author": "bea_AAPL_26",
          "url": "https://twitter.com/sample/aapl/26",
          "created_at": "2025-08-11T22:10:00+00:00",
          "text": "Selling $AAPL strength ahead of earnings—bearish skew.",
          "like_count": 314,
          "reply_count": 2,
          "repost_count": 63,
          "weight": -31.29,
          "engagement_level": "high"
        },
        {
          "id": "aapl_027",
          "source": "x",
          "symbol": "AAPL",
          "author": "neu_AAPL_27",
          "url": "https://twitter.com/sample/aapl/27",
          "created_at": "2025-08-11T22:15:00+00:00",
          "text": "$AAPL trading sideways pre-market; waiting for open to react.",
          "like_count": 318,
          "reply_count": 4,
          "repost_count": 64,
          "weight": 0.0,
          "engagement_level": "high"
        },
        {
          "id": "aapl_028",
          "source": "x",
          "symbol": "AAPL",
          "author": "neu_AAPL_28",
          "url": "https://twitter.com/sample/aapl/28",
          "created_at": "2025-08-11T22:20:00+00:00",
          "text": "Listening to $AAPL CFO interview—mostly reiterating last quarter.",
          "like_count": 331,
          "reply_count": 5,
          "repost_count": 70,
          "weight": 0.0,
          "engagement_level": "high"
        },
        {
          "id": "aapl_029",
          "source": "x",
          "symbol": "AAPL",
          "author": "neu_AAPL_29",
          "url": "https://twitter.com/sample/aapl/29",
          "created_at": "2025-08-11T22:25:00+00:00",
          "text": "No position in $AAPL right now; watching how it reacts to macro data.",
          "like_count": 344,
          "reply_count": 6,
          "repost_count": 76,
          "weight": 0.0,
          "engagement_level": "high"
        },
        {
          "id": "aapl_030",
          "source": "x",
          "symbol": "AAPL",
          "author": "neu_AAPL_30",
          "url": "https://twitter.com/sample/aapl/30",
          "created_at": "2025-08-11T22:30:00+00:00",
          "text": "$AAPL implied volatility flat, market pricing in quiet session.",
          "like_count": 7,
          "reply_count": 7,
          "repost_count": 2,
          "weight": 0.0,
          "engagement_level": "low"
        }
      ],
      "history": [
        {
          "timestamp": "2025-10-03T23:45:24.793845",
          "net_score": 64.15,
          "bullish_score": 159.91,
          "bearish_score": 92.11,
          "posts": 25,
          "change_pct": -0.88,
          "close": 21.68,
          "volume": 1043368.96
        },
        {
          "timestamp": "2025-10-04T00:45:24.793845",
          "net_score": 78.37,
          "bullish_score": 163.85,
          "bearish_score": 100.45,
          "posts": 24,
          "change_pct": 0.24,
          "close": 20.67,
          "volume": 1179334.79
        },
        {
          "timestamp": "2025-10-04T01:45:24.793845",
          "net_score": 81.44,
          "bullish_score": 161.67,
          "bearish_score": 82.2,
          "posts": 33,
          "change_pct": -1.81,
          "close": 19.25,
          "volume": 824301.25
        },
        {
          "timestamp": "2025-10-04T02:45:24.793845",
          "net_score": 46.06,
          "bullish_score": 139.51,
          "bearish_score": 76.13,
          "posts": 26,
          "change_pct": 2.84,
          "close": 18.77,
          "volume": 1099927.33
        },
        {
          "timestamp": "2025-10-04T03:45:24.793845",
          "net_score": 48.92,
          "bullish_score": 147.79,
          "bearish_score": 84.1,
          "posts": 28,
          "change_pct": 0.84,
          "close": 19.26,
          "volume": 1195679.53
        },
        {
          "timestamp": "2025-10-04T04:45:24.793845",
          "net_score": 74.35,
          "bullish_score": 165.86,
          "bearish_score": 74.65,
          "posts": 27,
          "change_pct": -1.74,
          "close": 19.86,
          "volume": 901777.54
        },
        {
          "timestamp": "2025-10-04T05:45:24.793845",
          "net_score": 45.45,
          "bullish_score": 148.74,
          "bearish_score": 99.1,
          "posts": 34,
          "change_pct": 1.11,
          "close": 20.29,
          "volume": 1049612.22
        },
        {
          "timestamp": "2025-10-04T06:45:24.793845",
          "net_score": 76.81,
          "bullish_score": 148.64,
          "bearish_score": 99.56,
          "posts": 24,
          "change_pct": 2.14,
          "close": 19.26,
          "volume": 1236513.98
        },
        {
          "timestamp": "2025-10-04T07:45:24.793845",
          "net_score": 73.12,
          "bullish_score": 152.0,
          "bearish_score": 73.72,
          "posts": 26,
          "change_pct": -1.13,
          "close": 21.02,
          "volume": 752775.51
        },
        {
          "timestamp": "2025-10-04T08:45:24.793845",
          "net_score": 67.22,
          "bullish_score": 141.63,
          "bearish_score": 100.13,
          "posts": 33,
          "change_pct": 0.39,
          "close": 20.22,
          "volume": 1153932.46
        },
        {
          "timestamp": "2025-10-04T09:45:24.793845",
          "net_score": 79.51,
          "bullish_score": 153.13,
          "bearish_score": 81.01,
          "posts": 33,
          "change_pct": -0.79,
          "close": 18.89,
          "volume": 942419.12
        },
        {
          "timestamp": "2025-10-04T10:45:24.793845",
          "net_score": 59.06,
          "bullish_score": 157.49,
          "bearish_score": 90.76,
          "posts": 24,
          "change_pct": -1.5,
          "close": 20.54,
          "volume": 1205153.84
        },
        {
          "timestamp": "2025-10-04T11:45:24.793845",
          "net_score": 83.16,
          "bullish_score": 155.99,
          "bearish_score": 90.29,
          "posts": 33,
          "change_pct": -1.35,
          "close": 21.01,
          "volume": 779755.91
        },
        {
          "timestamp": "2025-10-04T12:45:24.793845",
          "net_score": 55.71,
          "bullish_score": 148.53,
          "bearish_score": 75.17,
          "posts": 24,
          "change_pct": 1.85,
          "close": 20.55,
          "volume": 801886.12
        },
        {
          "timestamp": "2025-10-04T13:45:24.793845",
          "net_score": 54.78,
          "bullish_score": 162.57,
          "bearish_score": 90.67,
          "posts": 25,
          "change_pct": 2.67,
          "close": 21.84,
          "volume": 961496.5
        },
        {
          "timestamp": "2025-10-04T14:45:24.793845",
          "net_score": 59.67,
          "bullish_score": 165.72,
          "bearish_score": 100.98,
          "posts": 33,
          "change_pct": -2.39,
          "close": 21.52,
          "volume": 848677.7
        },
        {
          "timestamp": "2025-10-04T15:45:24.793845",
          "net_score": 61.02,
          "bullish_score": 147.58,
          "bearish_score": 95.02,
          "posts": 28,
          "change_pct": -0.14,
          "close": 21.62,
          "volume": 933731.1
        },
        {
          "timestamp": "2025-10-04T16:45:24.793845",
          "net_score": 70.02,
          "bullish_score": 140.57,
          "bearish_score": 89.54,
          "posts": 26,
          "change_pct": 2.71,
          "close": 19.67,
          "volume": 937836.13
        },
        {
          "timestamp": "2025-10-04T17:45:24.793845",
          "net_score": 50.27,
          "bullish_score": 158.19,
          "bearish_score": 81.24,
          "posts": 26,
          "change_pct": -1.95,
          "close": 19.17,
          "volume": 838411.62
        },
        {
          "timestamp": "2025-10-04T18:45:24.793845",
          "net_score": 51.57,
          "bullish_score": 155.56,
          "bearish_score": 89.1,
          "posts": 32,
          "change_pct": -1.1,
          "close": 21.27,
          "volume": 1001168.86
        },
        {
          "timestamp": "2025-10-04T19:45:24.793845",
          "net_score": 62.79,
          "bullish_score": 160.67,
          "bearish_score": 86.81,
          "posts": 27,
          "change_pct": -0.41,
          "close": 21.21,
          "volume": 837566.4
        },
        {
          "timestamp": "2025-10-04T20:45:24.793845",
          "net_score": 54.26,
          "bullish_score": 150.59,
          "bearish_score": 73.06,
          "posts": 32,
          "change_pct": -2.39,
          "close": 20.98,
          "volume": 1160686.98
        },
        {
          "timestamp": "2025-10-04T21:45:24.793845",
          "net_score": 70.57,
          "bullish_score": 166.28,
          "bearish_score": 100.93,
          "posts": 31,
          "change_pct": 2.69,
          "close": 20.94,
          "volume": 902679.33
        },
        {
          "timestamp": "2025-10-04T22:45:24.793845",
          "net_score": 47.06,
          "bullish_score": 163.83,
          "bearish_score": 98.89,
          "posts": 34,
          "change_pct": -2.79,
          "close": 21.96,
          "volume": 782533.39
        },
        {
          "timestamp": "2025-10-04T23:55:31.516642+00:00",
          "net_score": 64.77,
          "bullish_score": 151.71,
          "bearish_score": 86.94,
          "posts": 30,
          "change_pct": null,
          "close": null,
          "volume": null
        },
        {
          "timestamp": "2025-10-06T18:42:26.177144+00:00",
          "net_score": 64.77,
          "bullish_score": 151.71,
          "bearish_score": 86.94,
          "posts": 30,
          "change_pct": null,
          "close": null,
          "volume": null
        }
      ],
      "price": {}
    },
    "ONDS": {
      "summary": {
        "posts": 30,
        "bullish_score": 90.8,
        "bearish_score": 121.36,
        "net_score": -30.56,
        "bullish_posts": 13,
        "bearish_posts": 10,
        "neutral_posts": 7,
        "engagement_breakdown": {
          "high": 27,
          "medium": 2,
          "low": 1
        },
        "top_posts": [
          {
            "id": "onds_025",
            "author": "bea_ONDS_25",
            "created_at": "2025-08-13T15:05:00+00:00",
            "text": "$ONDS short setup triggered under 9.50.",
            "url": "https://twitter.com/sample/onds/25",
            "weight": -20.28,
            "sentiment": "bearish",
            "like_count": 307,
            "repost_count": 60,
            "engagement_level": "high"
          },
          {
            "id": "onds_014",
            "author": "bul_ONDS_14",
            "created_at": "2025-08-13T14:10:00+00:00",
            "text": "Bullish flow on $ONDS weekly calls—riding along.",
            "url": "https://twitter.com/sample/onds/14",
            "weight": 20.16,
            "sentiment": "bullish",
            "like_count": 187,
            "repost_count": 6,
            "engagement_level": "high"
          },
          {
            "id": "onds_024",
            "author": "bea_ONDS_24",
            "created_at": "2025-08-13T15:00:00+00:00",
            "text": "$ONDS below VWAP all day, bearish tone.",
            "url": "https://twitter.com/sample/onds/24",
            "weight": -19.16,
            "sentiment": "bearish",
            "like_count": 294,
            "repost_count": 54,
            "engagement_level": "high"
          },
          {
            "id": "onds_022",
            "author": "bea_ONDS_22",
            "created_at": "2025-08-13T14:50:00+00:00",
            "text": "$ONDS dump after midday rumors; I'm short.",
            "url": "https://twitter.com/sample/onds/22",
            "weight": -16.92,
            "sentiment": "bearish",
            "like_count": 268,
            "repost_count": 42,
            "engagement_level": "high"
          },
          {
            "id": "onds_018",
            "author": "bea_ONDS_18",
            "created_at": "2025-08-13T14:30:00+00:00",
            "text": "Shorting $ONDS into resistance; risk/reward favors bears.",
            "url": "https://twitter.com/sample/onds/18",
            "weight": -12.44,
            "sentiment": "bearish",
            "like_count": 216,
            "repost_count": 18,
            "engagement_level": "high"
          }
        ]
      },
      "posts": [
        {
          "id": "onds_001",
          "source": "x",
          "symbol": "ONDS",
          "author": "bul_ONDS_1",
          "url": "https://twitter.com/sample/onds/1",
          "created_at": "2025-08-13T13:05:00+00:00",
          "text": "$ONDS bulls showing up after that pilot contract win.",
          "like_count": 18,
          "reply_count": 2,
          "repost_count": 8,
          "weight": 1.76,
          "engagement_level": "medium"
        },
        {
          "id": "onds_002",
          "source": "x",
          "symbol": "ONDS",
          "author": "bul_ONDS_2",
          "url": "https://twitter.com/sample/onds/2",
          "created_at": "2025-08-13T13:10:00+00:00",
          "text": "Small cap radar: $ONDS breaking out, taking a long starter.",
          "like_count": 31,
          "reply_count": 3,
          "repost_count": 14,
          "weight": 2.32,
          "engagement_level": "medium"
        },
        {
          "id": "onds_003",
          "source": "x",
          "symbol": "ONDS",
          "author": "bul_ONDS_3",
          "url": "https://twitter.com/sample/onds/3",
          "created_at": "2025-08-13T13:15:00+00:00",
          "text": "$ONDS buy volume surging—green all morning.",
          "like_count": 44,
          "reply_count": 4,
          "repost_count": 20,
          "weight": 5.76,
          "engagement_level": "high"
        },
        {
          "id": "onds_004",
          "source": "x",
          "symbol": "ONDS",
          "author": "bul_ONDS_4",
          "url": "https://twitter.com/sample/onds/4",
          "created_at": "2025-08-13T13:20:00+00:00",
          "text": "$ONDS CEO interview sounded bullish on pipeline deployments.",
          "like_count": 57,
          "reply_count": 5,
          "repost_count": 26,
          "weight": 6.88,
          "engagement_level": "high"
        },
        {
          "id": "onds_005",
          "source": "x",
          "symbol": "ONDS",
          "author": "bul_ONDS_5",
          "url": "https://twitter.com/sample/onds/5",
          "created_at": "2025-08-13T13:25:00+00:00",
          "text": "Adding $ONDS calls; love the long-term spectrum story.",
          "like_count": 70,
          "reply_count": 6,
          "repost_count": 32,
          "weight": 8.0,
          "engagement_level": "high"
        },
        {
          "id": "onds_006",
          "source": "x",
          "symbol": "ONDS",
          "author": "bul_ONDS_6",
          "url": "https://twitter.com/sample/onds/6",
          "created_at": "2025-08-13T13:30:00+00:00",
          "text": "$ONDS mooning after that infrastructure update.",
          "like_count": 83,
          "reply_count": 7,
          "repost_count": 38,
          "weight": 4.56,
          "engagement_level": "high"
        },
        {
          "id": "onds_007",
          "source": "x",
          "symbol": "ONDS",
          "author": "bul_ONDS_7",
          "url": "https://twitter.com/sample/onds/7",
          "created_at": "2025-08-13T13:35:00+00:00",
          "text": "$ONDS long play working; closing in on prior resistance.",
          "like_count": 96,
          "reply_count": 8,
          "repost_count": 44,
          "weight": 5.12,
          "engagement_level": "high"
        },
        {
          "id": "onds_008",
          "source": "x",
          "symbol": "ONDS",
          "author": "bul_ONDS_8",
          "url": "https://twitter.com/sample/onds/8",
          "created_at": "2025-08-13T13:40:00+00:00",
          "text": "Institutional prints hitting the tape on $ONDS—bullish read.",
          "like_count": 109,
          "reply_count": 9,
          "repost_count": 50,
          "weight": 11.36,
          "engagement_level": "high"
        },
        {
          "id": "onds_009",
          "source": "x",
          "symbol": "ONDS",
          "author": "bul_ONDS_9",
          "url": "https://twitter.com/sample/onds/9",
          "created_at": "2025-08-13T13:45:00+00:00",
          "text": "$ONDS accumulation pattern continues; staying long.",
          "like_count": 122,
          "reply_count": 10,
          "repost_count": 56,
          "weight": 6.24,
          "engagement_level": "high"
        },
        {
          "id": "onds_010",
          "source": "x",
          "symbol": "ONDS",
          "author": "bul_ONDS_10",
          "url": "https://twitter.com/sample/onds/10",
          "created_at": "2025-08-13T13:50:00+00:00",
          "text": "$ONDS guidance raise has me buying this dip.",
          "like_count": 135,
          "reply_count": 11,
          "repost_count": 62,
          "weight": 6.8,
          "engagement_level": "high"
        },
        {
          "id": "onds_011",
          "source": "x",
          "symbol": "ONDS",
          "author": "bul_ONDS_11",
          "url": "https://twitter.com/sample/onds/11",
          "created_at": "2025-08-13T13:55:00+00:00",
          "text": "Keeping $ONDS long; recurring revenue story compelling.",
          "like_count": 148,
          "reply_count": 12,
          "repost_count": 68,
          "weight": 7.36,
          "engagement_level": "high"
        },
        {
          "id": "onds_012",
          "source": "x",
          "symbol": "ONDS",
          "author": "bul_ONDS_12",
          "url": "https://twitter.com/sample/onds/12",
          "created_at": "2025-08-13T14:00:00+00:00",
          "text": "$ONDS short interest falling fast—bulls in charge.",
          "like_count": 161,
          "reply_count": 0,
          "repost_count": 74,
          "weight": 0.0,
          "engagement_level": "high"
        },
        {
          "id": "onds_013",
          "source": "x",
          "symbol": "ONDS",
          "author": "bul_ONDS_13",
          "url": "https://twitter.com/sample/onds/13",
          "created_at": "2025-08-13T14:05:00+00:00",
          "text": "$ONDS green for fourth straight session; trend strong.",
          "like_count": 174,
          "reply_count": 1,
          "repost_count": 0,
          "weight": 4.48,
          "engagement_level": "high"
        },
        {
          "id": "onds_014",
          "source": "x",
          "symbol": "ONDS",
          "author": "bul_ONDS_14",
          "url": "https://twitter.com/sample/onds/14",
          "created_at": "2025-08-13T14:10:00+00:00",
          "text": "Bullish flow on $ONDS weekly calls—riding along.",
          "like_count": 187,
          "reply_count": 2,
          "repost_count": 6,
          "weight": 20.16,
          "engagement_level": "high"
        },
        {
          "id": "onds_015",
          "source": "x",
          "symbol": "ONDS",
          "author": "bul_ONDS_15",
          "url": "https://twitter.com/sample/onds/15",
          "created_at": "2025-08-13T14:15:00+00:00",
          "text": "$ONDS uptrend intact, loading more shares.",
          "like_count": 200,
          "reply_count": 3,
          "repost_count": 12,
          "weight": 0.0,
          "engagement_level": "high"
        },
        {
          "id": "onds_016",
          "source": "x",
          "symbol": "ONDS",
          "author": "bea_ONDS_16",
          "url": "https://twitter.com/sample/onds/16",
          "created_at": "2025-08-13T14:20:00+00:00",
          "text": "$ONDS bearish divergence on RSI—took profits.",
          "like_count": 190,
          "reply_count": 5,
          "repost_count": 6,
          "weight": -10.2,
          "engagement_level": "high"
        },
        {
          "id": "onds_017",
          "source": "x",
          "symbol": "ONDS",
          "author": "bea_ONDS_17",
          "url": "https://twitter.com/sample/onds/17",
          "created_at": "2025-08-13T14:25:00+00:00",
          "text": "$ONDS red after that downtick in backlog; short-term concerning.",
          "like_count": 203,
          "reply_count": 6,
          "repost_count": 12,
          "weight": -11.32,
          "engagement_level": "high"
        },
        {
          "id": "onds_018",
          "source": "x",
          "symbol": "ONDS",
          "author": "bea_ONDS_18",
          "url": "https://twitter.com/sample/onds/18",
          "created_at": "2025-08-13T14:30:00+00:00",
          "text": "Shorting $ONDS into resistance; risk/reward favors bears.",
          "like_count": 216,
          "reply_count": 7,
          "repost_count": 18,
          "weight": -12.44,
          "engagement_level": "high"
        },
        {
          "id": "onds_019",
          "source": "x",
          "symbol": "ONDS",
          "author": "bea_ONDS_19",
          "url": "https://twitter.com/sample/onds/19",
          "created_at": "2025-08-13T14:35:00+00:00",
          "text": "Heavy selling in $ONDS, maybe insiders exiting.",
          "like_count": 229,
          "reply_count": 8,
          "repost_count": 24,
          "weight": -6.78,
          "engagement_level": "high"
        },
        {
          "id": "onds_020",
          "source": "x",
          "symbol": "ONDS",
          "author": "bea_ONDS_20",
          "url": "https://twitter.com/sample/onds/20",
          "created_at": "2025-08-13T14:40:00+00:00",
          "text": "$ONDS bear case is execution risk; staying on sidelines.",
          "like_count": 242,
          "reply_count": 9,
          "repost_count": 30,
          "weight": -7.34,
          "engagement_level": "high"
        },
        {
          "id": "onds_021",
          "source": "x",
          "symbol": "ONDS",
          "author": "bea_ONDS_21",
          "url": "https://twitter.com/sample/onds/21",
          "created_at": "2025-08-13T14:45:00+00:00",
          "text": "Opened $ONDS puts—expect mean reversion.",
          "like_count": 255,
          "reply_count": 10,
          "repost_count": 36,
          "weight": -7.9,
          "engagement_level": "high"
        },
        {
          "id": "onds_022",
          "source": "x",
          "symbol": "ONDS",
          "author": "bea_ONDS_22",
          "url": "https://twitter.com/sample/onds/22",
          "created_at": "2025-08-13T14:50:00+00:00",
          "text": "$ONDS dump after midday rumors; I'm short.",
          "like_count": 268,
          "reply_count": 11,
          "repost_count": 42,
          "weight": -16.92,
          "engagement_level": "high"
        },
        {
          "id": "onds_023",
          "source": "x",
          "symbol": "ONDS",
          "author": "bea_ONDS_23",
          "url": "https://twitter.com/sample/onds/23",
          "created_at": "2025-08-13T14:55:00+00:00",
          "text": "$ONDS guidance still light; bears might press this lower.",
          "like_count": 281,
          "reply_count": 12,
          "repost_count": 48,
          "weight": -9.02,
          "engagement_level": "high"
        },
        {
          "id": "onds_024",
          "source": "x",
          "symbol": "ONDS",
          "author": "bea_ONDS_24",
          "url": "https://twitter.com/sample/onds/24",
          "created_at": "2025-08-13T15:00:00+00:00",
          "text": "$ONDS below VWAP all day, bearish tone.",
          "like_count": 294,
          "reply_count": 0,
          "repost_count": 54,
          "weight": -19.16,
          "engagement_level": "high"
        },
        {
          "id": "onds_025",
          "source": "x",
          "symbol": "ONDS",
          "author": "bea_ONDS_25",
          "url": "https://twitter.com/sample/onds/25",
          "created_at": "2025-08-13T15:05:00+00:00",
          "text": "$ONDS short setup triggered under 9.50.",
          "like_count": 307,
          "reply_count": 1,
          "repost_count": 60,
          "weight": -20.28,
          "engagement_level": "high"
        },
        {
          "id": "onds_026",
          "source": "x",
          "symbol": "ONDS",
          "author": "neu_ONDS_26",
          "url": "https://twitter.com/sample/onds/26",
          "created_at": "2025-08-13T15:10:00+00:00",
          "text": "$ONDS hovering near 9.80; waiting for break either way.",
          "like_count": 307,
          "reply_count": 3,
          "repost_count": 59,
          "weight": 0.0,
          "engagement_level": "high"
        },
        {
          "id": "onds_027",
          "source": "x",
          "symbol": "ONDS",
          "author": "neu_ONDS_27",
          "url": "https://twitter.com/sample/onds/27",
          "created_at": "2025-08-13T15:15:00+00:00",
          "text": "Listening to $ONDS presentation—lots of technical detail, no surprises.",
          "like_count": 320,
          "reply_count": 4,
          "repost_count": 65,
          "weight": 0.0,
          "engagement_level": "high"
        },
        {
          "id": "onds_028",
          "source": "x",
          "symbol": "ONDS",
          "author": "neu_ONDS_28",
          "url": "https://twitter.com/sample/onds/28",
          "created_at": "2025-08-13T15:20:00+00:00",
          "text": "$ONDS volume average so far; market undecided.",
          "like_count": 333,
          "reply_count": 5,
          "repost_count": 71,
          "weight": 0.0,
          "engagement_level": "high"
        },
        {
          "id": "onds_029",
          "source": "x",
          "symbol": "ONDS",
          "author": "neu_ONDS_29",
          "url": "https://twitter.com/sample/onds/29",
          "created_at": "2025-08-13T15:25:00+00:00",
          "text": "Watching $ONDS order book; two-sided flow right now.",
          "like_count": 346,
          "reply_count": 6,
          "repost_count": 77,
          "weight": 0.0,
          "engagement_level": "high"
        },
        {
          "id": "onds_030",
          "source": "x",
          "symbol": "ONDS",
          "author": "neu_ONDS_30",
          "url": "https://twitter.com/sample/onds/30",
          "created_at": "2025-08-13T15:30:00+00:00",
          "text": "No trade on $ONDS yet; waiting for catalyst clarity.",
          "like_count": 9,
          "reply_count": 7,
          "repost_count": 3,
          "weight": 0.0,
          "engagement_level": "low"
        }
      ],
      "history": [
        {
          "timestamp": "2025-10-03T23:45:24.793845",
          "net_score": -24.09,
          "bullish_score": 101.47,
          "bearish_score": 108.43,
          "posts": 31,
          "change_pct": 1.64,
          "close": 19.54,
          "volume": 942030.82
        },
        {
          "timestamp": "2025-10-04T00:45:24.793845",
          "net_score": -39.49,
          "bullish_score": 93.45,
          "bearish_score": 107.28,
          "posts": 35,
          "change_pct": -0.73,
          "close": 20.99,
          "volume": 898689.59
        },
        {
          "timestamp": "2025-10-04T01:45:24.793845",
          "net_score": -26.16,
          "bullish_score": 79.16,
          "bearish_score": 119.92,
          "posts": 35,
          "change_pct": -2.35,
          "close": 19.63,
          "volume": 1061578.48
        },
        {
          "timestamp": "2025-10-04T02:45:24.793845",
          "net_score": -31.31,
          "bullish_score": 85.21,
          "bearish_score": 123.13,
          "posts": 28,
          "change_pct": 0.74,
          "close": 19.18,
          "volume": 1089721.04
        },
        {
          "timestamp": "2025-10-04T03:45:24.793845",
          "net_score": -45.25,
          "bullish_score": 80.48,
          "bearish_score": 122.21,
          "posts": 30,
          "change_pct": -0.95,
          "close": 18.61,
          "volume": 1024478.05
        },
        {
          "timestamp": "2025-10-04T04:45:24.793845",
          "net_score": -38.91,
          "bullish_score": 87.0,
          "bearish_score": 124.66,
          "posts": 30,
          "change_pct": 0.27,
          "close": 18.93,
          "volume": 846097.18
        },
        {
          "timestamp": "2025-10-04T05:45:24.793845",
          "net_score": -24.38,
          "bullish_score": 105.17,
          "bearish_score": 127.84,
          "posts": 35,
          "change_pct": 1.2,
          "close": 20.74,
          "volume": 1147007.34
        },
        {
          "timestamp": "2025-10-04T06:45:24.793845",
          "net_score": -40.29,
          "bullish_score": 94.26,
          "bearish_score": 125.22,
          "posts": 35,
          "change_pct": -0.02,
          "close": 21.37,
          "volume": 1243294.68
        },
        {
          "timestamp": "2025-10-04T07:45:24.793845",
          "net_score": -17.88,
          "bullish_score": 100.74,
          "bearish_score": 127.33,
          "posts": 25,
          "change_pct": 2.99,
          "close": 20.54,
          "volume": 889944.19
        },
        {
          "timestamp": "2025-10-04T08:45:24.793845",
          "net_score": -46.21,
          "bullish_score": 76.95,
          "bearish_score": 125.84,
          "posts": 35,
          "change_pct": 0.74,
          "close": 19.9,
          "volume": 731042.15
        },
        {
          "timestamp": "2025-10-04T09:45:24.793845",
          "net_score": -43.44,
          "bullish_score": 98.17,
          "bearish_score": 117.55,
          "posts": 35,
          "change_pct": 2.13,
          "close": 21.92,
          "volume": 1025910.12
        },
        {
          "timestamp": "2025-10-04T10:45:24.793845",
          "net_score": -14.25,
          "bullish_score": 92.45,
          "bearish_score": 125.17,
          "posts": 31,
          "change_pct": -0.2,
          "close": 20.48,
          "volume": 951480.74
        },
        {
          "timestamp": "2025-10-04T11:45:24.793845",
          "net_score": -16.7,
          "bullish_score": 93.37,
          "bearish_score": 134.58,
          "posts": 34,
          "change_pct": 2.36,
          "close": 21.52,
          "volume": 1276729.65
        },
        {
          "timestamp": "2025-10-04T12:45:24.793845",
          "net_score": -39.66,
          "bullish_score": 97.49,
          "bearish_score": 120.39,
          "posts": 28,
          "change_pct": -0.04,
          "close": 19.36,
          "volume": 784645.63
        },
        {
          "timestamp": "2025-10-04T13:45:24.793845",
          "net_score": -11.29,
          "bullish_score": 98.02,
          "bearish_score": 112.48,
          "posts": 34,
          "change_pct": 2.78,
          "close": 21.85,
          "volume": 1095317.47
        },
        {
          "timestamp": "2025-10-04T14:45:24.793845",
          "net_score": -48.99,
          "bullish_score": 97.0,
          "bearish_score": 113.52,
          "posts": 34,
          "change_pct": 2.13,
          "close": 18.99,
          "volume": 744276.68
        },
        {
          "timestamp": "2025-10-04T15:45:24.793845",
          "net_score": -39.97,
          "bullish_score": 94.52,
          "bearish_score": 116.53,
          "posts": 33,
          "change_pct": -2.33,
          "close": 19.22,
          "volume": 1267809.56
        },
        {
          "timestamp": "2025-10-04T16:45:24.793845",
          "net_score": -29.71,
          "bullish_score": 91.38,
          "bearish_score": 108.9,
          "posts": 32,
          "change_pct": -2.46,
          "close": 20.24,
          "volume": 1021743.54
        },
        {
          "timestamp": "2025-10-04T17:45:24.793845",
          "net_score": -16.6,
          "bullish_score": 98.82,
          "bearish_score": 115.31,
          "posts": 35,
          "change_pct": 0.3,
          "close": 18.05,
          "volume": 1241040.6
        },
        {
          "timestamp": "2025-10-04T18:45:24.793845",
          "net_score": -14.95,
          "bullish_score": 81.3,
          "bearish_score": 119.91,
          "posts": 28,
          "change_pct": -2.54,
          "close": 20.9,
          "volume": 849925.74
        },
        {
          "timestamp": "2025-10-04T19:45:24.793845",
          "net_score": -26.7,
          "bullish_score": 76.32,
          "bearish_score": 134.18,
          "posts": 35,
          "change_pct": -0.69,
          "close": 20.6,
          "volume": 1077876.13
        },
        {
          "timestamp": "2025-10-04T20:45:24.793845",
          "net_score": -16.98,
          "bullish_score": 82.04,
          "bearish_score": 129.71,
          "posts": 35,
          "change_pct": -1.75,
          "close": 18.73,
          "volume": 708844.04
        },
        {
          "timestamp": "2025-10-04T21:45:24.793845",
          "net_score": -26.16,
          "bullish_score": 93.33,
          "bearish_score": 125.93,
          "posts": 30,
          "change_pct": -0.26,
          "close": 20.05,
          "volume": 925155.65
        },
        {
          "timestamp": "2025-10-04T22:45:24.793845",
          "net_score": -40.03,
          "bullish_score": 78.2,
          "bearish_score": 131.17,
          "posts": 24,
          "change_pct": 0.95,
          "close": 19.56,
          "volume": 1114538.3
        },
        {
          "timestamp": "2025-10-04T23:55:31.516642+00:00",
          "net_score": -30.56,
          "bullish_score": 90.8,
          "bearish_score": 121.36,
          "posts": 30,
          "change_pct": null,
          "close": null,
          "volume": null
        },
        {
          "timestamp": "2025-10-06T18:42:26.177144+00:00",
          "net_score": -30.56,
          "bullish_score": 90.8,
          "bearish_score": 121.36,
          "posts": 30,
          "change_pct": null,
          "close": null,
          "volume": null
        }
      ],
      "price": {}
    }
  },
  "history": {
    "IXHL": [
      {
        "timestamp": "2025-10-03T23:45:24.793845",
        "net_score": 97.88,
        "bullish_score": 192.94,
        "bearish_score": 94.66,
        "posts": 32,
        "change_pct": 0.64,
        "close": 19.45,
        "volume": 820512.32
      },
      {
        "timestamp": "2025-10-04T00:45:24.793845",
        "net_score": 85.86,
        "bullish_score": 213.31,
        "bearish_score": 107.5,
        "posts": 33,
        "change_pct": 0.84,
        "close": 21.2,
        "volume": 1278508.76
      },
      {
        "timestamp": "2025-10-04T01:45:24.793845",
        "net_score": 105.3,
        "bullish_score": 207.71,
        "bearish_score": 105.52,
        "posts": 30,
        "change_pct": -0.57,
        "close": 18.13,
        "volume": 816446.99
      },
      {
        "timestamp": "2025-10-04T02:45:24.793845",
        "net_score": 91.98,
        "bullish_score": 192.24,
        "bearish_score": 100.89,
        "posts": 35,
        "change_pct": 0.54,
        "close": 21.57,
        "volume": 848194.97
      },
      {
        "timestamp": "2025-10-04T03:45:24.793845",
        "net_score": 103.43,
        "bullish_score": 197.89,
        "bearish_score": 105.92,
        "posts": 35,
        "change_pct": 1.25,
        "close": 20.91,
        "volume": 1057630.15
      },
      {
        "timestamp": "2025-10-04T04:45:24.793845",
        "net_score": 90.38,
        "bullish_score": 210.92,
        "bearish_score": 116.87,
        "posts": 32,
        "change_pct": 1.02,
        "close": 19.89,
        "volume": 814823.69
      },
      {
        "timestamp": "2025-10-04T05:45:24.793845",
        "net_score": 102.64,
        "bullish_score": 194.87,
        "bearish_score": 92.32,
        "posts": 31,
        "change_pct": -0.48,
        "close": 18.36,
        "volume": 932200.43
      },
      {
        "timestamp": "2025-10-04T06:45:24.793845",
        "net_score": 93.22,
        "bullish_score": 193.58,
        "bearish_score": 103.49,
        "posts": 30,
        "change_pct": 1.61,
        "close": 19.73,
        "volume": 1223095.45
      },
      {
        "timestamp": "2025-10-04T07:45:24.793845",
        "net_score": 108.11,
        "bullish_score": 204.56,
        "bearish_score": 104.34,
        "posts": 25,
        "change_pct": 0.12,
        "close": 20.69,
        "volume": 1293882.42
      },
      {
        "timestamp": "2025-10-04T08:45:24.793845",
        "net_score": 92.84,
        "bullish_score": 214.6,
        "bearish_score": 115.15,
        "posts": 34,
        "change_pct": 0.05,
        "close": 19.98,
        "volume": 1109122.81
      },
      {
        "timestamp": "2025-10-04T09:45:24.793845",
        "net_score": 112.56,
        "bullish_score": 203.02,
        "bearish_score": 119.9,
        "posts": 28,
        "change_pct": 0.17,
        "close": 20.8,
        "volume": 957859.13
      },
      {
        "timestamp": "2025-10-04T10:45:24.793845",
        "net_score": 74.98,
        "bullish_score": 198.54,
        "bearish_score": 105.69,
        "posts": 29,
        "change_pct": 0.78,
        "close": 18.11,
        "volume": 877577.5
      },
      {
        "timestamp": "2025-10-04T11:45:24.793845",
        "net_score": 90.36,
        "bullish_score": 195.02,
        "bearish_score": 103.94,
        "posts": 36,
        "change_pct": 0.83,
        "close": 20.28,
        "volume": 873470.53
      },
      {
        "timestamp": "2025-10-04T12:45:24.793845",
        "net_score": 110.44,
        "bullish_score": 192.67,
        "bearish_score": 106.78,
        "posts": 30,
        "change_pct": -2.25,
        "close": 20.97,
        "volume": 707763.13
      },
      {
        "timestamp": "2025-10-04T13:45:24.793845",
        "net_score": 77.84,
        "bullish_score": 208.22,
        "bearish_score": 92.78,
        "posts": 26,
        "change_pct": 2.27,
        "close": 19.36,
        "volume": 1150010.88
      },
      {
        "timestamp": "2025-10-04T14:45:24.793845",
        "net_score": 103.17,
        "bullish_score": 203.71,
        "bearish_score": 114.67,
        "posts": 33,
        "change_pct": 1.52,
        "close": 19.63,
        "volume": 1161078.74
      },
      {
        "timestamp": "2025-10-04T15:45:24.793845",
        "net_score": 79.58,
        "bullish_score": 207.68,
        "bearish_score": 115.66,
        "posts": 26,
        "change_pct": 0.5,
        "close": 18.93,
        "volume": 1250572.64
      },
      {
        "timestamp": "2025-10-04T16:45:24.793845",
        "net_score": 85.19,
        "bullish_score": 214.99,
        "bearish_score": 92.96,
        "posts": 35,
        "change_pct": -2.34,
        "close": 21.8,
        "volume": 1142736.5
      },
      {
        "timestamp": "2025-10-04T17:45:24.793845",
        "net_score": 85.4,
        "bullish_score": 193.3,
        "bearish_score": 100.92,
        "posts": 27,
        "change_pct": -1.44,
        "close": 20.8,
        "volume": 786043.93
      },
      {
        "timestamp": "2025-10-04T18:45:24.793845",
        "net_score": 105.62,
        "bullish_score": 214.09,
        "bearish_score": 109.53,
        "posts": 29,
        "change_pct": -1.39,
        "close": 18.28,
        "volume": 1031229.89
      },
      {
        "timestamp": "2025-10-04T19:45:24.793845",
        "net_score": 88.65,
        "bullish_score": 201.37,
        "bearish_score": 111.81,
        "posts": 26,
        "change_pct": 1.56,
        "close": 18.86,
        "volume": 721186.87
      },
      {
        "timestamp": "2025-10-04T20:45:24.793845",
        "net_score": 91.9,
        "bullish_score": 212.56,
        "bearish_score": 103.89,
        "posts": 28,
        "change_pct": -1.54,
        "close": 21.46,
        "volume": 957525.86
      },
      {
        "timestamp": "2025-10-04T21:45:24.793845",
        "net_score": 80.17,
        "bullish_score": 213.42,
        "bearish_score": 104.55,
        "posts": 24,
        "change_pct": 0.73,
        "close": 21.28,
        "volume": 764913.13
      },
      {
        "timestamp": "2025-10-04T22:45:24.793845",
        "net_score": 74.8,
        "bullish_score": 208.81,
        "bearish_score": 108.38,
        "posts": 32,
        "change_pct": 0.6,
        "close": 20.06,
        "volume": 737425.25
      },
      {
        "timestamp": "2025-10-04T23:55:31.516642+00:00",
        "net_score": 92.75,
        "bullish_score": 200.07,
        "bearish_score": 107.32,
        "posts": 30,
        "change_pct": null,
        "close": null,
        "volume": null
      },
      {
        "timestamp": "2025-10-06T18:42:26.177144+00:00",
        "net_score": 92.75,
        "bullish_score": 200.07,
        "bearish_score": 107.32,
        "posts": 30,
        "change_pct": null,
        "close": null,
        "volume": null
      }
    ],
    "AAPL": [
      {
        "timestamp": "2025-10-03T23:45:24.793845",
        "net_score": 64.15,
        "bullish_score": 159.91,
        "bearish_score": 92.11,
        "posts": 25,
        "change_pct": -0.88,
        "close": 21.68,
        "volume": 1043368.96
      },
      {
        "timestamp": "2025-10-04T00:45:24.793845",
        "net_score": 78.37,
        "bullish_score": 163.85,
        "bearish_score": 100.45,
        "posts": 24,
        "change_pct": 0.24,
        "close": 20.67,
        "volume": 1179334.79
      },
      {
        "timestamp": "2025-10-04T01:45:24.793845",
        "net_score": 81.44,
        "bullish_score": 161.67,
        "bearish_score": 82.2,
        "posts": 33,
        "change_pct": -1.81,
        "close": 19.25,
        "volume": 824301.25
      },
      {
        "timestamp": "2025-10-04T02:45:24.793845",
        "net_score": 46.06,
        "bullish_score": 139.51,
        "bearish_score": 76.13,
        "posts": 26,
        "change_pct": 2.84,
        "close": 18.77,
        "volume": 1099927.33
      },
      {
        "timestamp": "2025-10-04T03:45:24.793845",
        "net_score": 48.92,
        "bullish_score": 147.79,
        "bearish_score": 84.1,
        "posts": 28,
        "change_pct": 0.84,
        "close": 19.26,
        "volume": 1195679.53
      },
      {
        "timestamp": "2025-10-04T04:45:24.793845",
        "net_score": 74.35,
        "bullish_score": 165.86,
        "bearish_score": 74.65,
        "posts": 27,
        "change_pct": -1.74,
        "close": 19.86,
        "volume": 901777.54
      },
      {
        "timestamp": "2025-10-04T05:45:24.793845",
        "net_score": 45.45,
        "bullish_score": 148.74,
        "bearish_score": 99.1,
        "posts": 34,
        "change_pct": 1.11,
        "close": 20.29,
        "volume": 1049612.22
      },
      {
        "timestamp": "2025-10-04T06:45:24.793845",
        "net_score": 76.81,
        "bullish_score": 148.64,
        "bearish_score": 99.56,
        "posts": 24,
        "change_pct": 2.14,
        "close": 19.26,
        "volume": 1236513.98
      },
      {
        "timestamp": "2025-10-04T07:45:24.793845",
        "net_score": 73.12,
        "bullish_score": 152.0,
        "bearish_score": 73.72,
        "posts": 26,
        "change_pct": -1.13,
        "close": 21.02,
        "volume": 752775.51
      },
      {
        "timestamp": "2025-10-04T08:45:24.793845",
        "net_score": 67.22,
        "bullish_score": 141.63,
        "bearish_score": 100.13,
        "posts": 33,
        "change_pct": 0.39,
        "close": 20.22,
        "volume": 1153932.46
      },
      {
        "timestamp": "2025-10-04T09:45:24.793845",
        "net_score": 79.51,
        "bullish_score": 153.13,
        "bearish_score": 81.01,
        "posts": 33,
        "change_pct": -0.79,
        "close": 18.89,
        "volume": 942419.12
      },
      {
        "timestamp": "2025-10-04T10:45:24.793845",
        "net_score": 59.06,
        "bullish_score": 157.49,
        "bearish_score": 90.76,
        "posts": 24,
        "change_pct": -1.5,
        "close": 20.54,
        "volume": 1205153.84
      },
      {
        "timestamp": "2025-10-04T11:45:24.793845",
        "net_score": 83.16,
        "bullish_score": 155.99,
        "bearish_score": 90.29,
        "posts": 33,
        "change_pct": -1.35,
        "close": 21.01,
        "volume": 779755.91
      },
      {
        "timestamp": "2025-10-04T12:45:24.793845",
        "net_score": 55.71,
        "bullish_score": 148.53,
        "bearish_score": 75.17,
        "posts": 24,
        "change_pct": 1.85,
        "close": 20.55,
        "volume": 801886.12
      },
      {
        "timestamp": "2025-10-04T13:45:24.793845",
        "net_score": 54.78,
        "bullish_score": 162.57,
        "bearish_score": 90.67,
        "posts": 25,
        "change_pct": 2.67,
        "close": 21.84,
        "volume": 961496.5
      },
      {
        "timestamp": "2025-10-04T14:45:24.793845",
        "net_score": 59.67,
        "bullish_score": 165.72,
        "bearish_score": 100.98,
        "posts": 33,
        "change_pct": -2.39,
        "close": 21.52,
        "volume": 848677.7
      },
      {
        "timestamp": "2025-10-04T15:45:24.793845",
        "net_score": 61.02,
        "bullish_score": 147.58,
        "bearish_score": 95.02,
        "posts": 28,
        "change_pct": -0.14,
        "close": 21.62,
        "volume": 933731.1
      },
      {
        "timestamp": "2025-10-04T16:45:24.793845",
        "net_score": 70.02,
        "bullish_score": 140.57,
        "bearish_score": 89.54,
        "posts": 26,
        "change_pct": 2.71,
        "close": 19.67,
        "volume": 937836.13
      },
      {
        "timestamp": "2025-10-04T17:45:24.793845",
        "net_score": 50.27,
        "bullish_score": 158.19,
        "bearish_score": 81.24,
        "posts": 26,
        "change_pct": -1.95,
        "close": 19.17,
        "volume": 838411.62
      },
      {
        "timestamp": "2025-10-04T18:45:24.793845",
        "net_score": 51.57,
        "bullish_score": 155.56,
        "bearish_score": 89.1,
        "posts": 32,
        "change_pct": -1.1,
        "close": 21.27,
        "volume": 1001168.86
      },
      {
        "timestamp": "2025-10-04T19:45:24.793845",
        "net_score": 62.79,
        "bullish_score": 160.67,
        "bearish_score": 86.81,
        "posts": 27,
        "change_pct": -0.41,
        "close": 21.21,
        "volume": 837566.4
      },
      {
        "timestamp": "2025-10-04T20:45:24.793845",
        "net_score": 54.26,
        "bullish_score": 150.59,
        "bearish_score": 73.06,
        "posts": 32,
        "change_pct": -2.39,
        "close": 20.98,
        "volume": 1160686.98
      },
      {
        "timestamp": "2025-10-04T21:45:24.793845",
        "net_score": 70.57,
        "bullish_score": 166.28,
        "bearish_score": 100.93,
        "posts": 31,
        "change_pct": 2.69,
        "close": 20.94,
        "volume": 902679.33
      },
      {
        "timestamp": "2025-10-04T22:45:24.793845",
        "net_score": 47.06,
        "bullish_score": 163.83,
        "bearish_score": 98.89,
        "posts": 34,
        "change_pct": -2.79,
        "close": 21.96,
        "volume": 782533.39
      },
      {
        "timestamp": "2025-10-04T23:55:31.516642+00:00",
        "net_score": 64.77,
        "bullish_score": 151.71,
        "bearish_score": 86.94,
        "posts": 30,
        "change_pct": null,
        "close": null,
        "volume": null
      },
      {
        "timestamp": "2025-10-06T18:42:26.177144+00:00",
        "net_score": 64.77,
        "bullish_score": 151.71,
        "bearish_score": 86.94,
        "posts": 30,
        "change_pct": null,
        "close": null,
        "volume": null
      }
    ],
    "ONDS": [
      {
        "timestamp": "2025-10-03T23:45:24.793845",
        "net_score": -24.09,
        "bullish_score": 101.47,
        "bearish_score": 108.43,
        "posts": 31,
        "change_pct": 1.64,
        "close": 19.54,
        "volume": 942030.82
      },
      {
        "timestamp": "2025-10-04T00:45:24.793845",
        "net_score": -39.49,
        "bullish_score": 93.45,
        "bearish_score": 107.28,
        "posts": 35,
        "change_pct": -0.73,
        "close": 20.99,
        "volume": 898689.59
      },
      {
        "timestamp": "2025-10-04T01:45:24.793845",
        "net_score": -26.16,
        "bullish_score": 79.16,
        "bearish_score": 119.92,
        "posts": 35,
        "change_pct": -2.35,
        "close": 19.63,
        "volume": 1061578.48
      },
      {
        "timestamp": "2025-10-04T02:45:24.793845",
        "net_score": -31.31,
        "bullish_score": 85.21,
        "bearish_score": 123.13,
        "posts": 28,
        "change_pct": 0.74,
        "close": 19.18,
        "volume": 1089721.04
      },
      {
        "timestamp": "2025-10-04T03:45:24.793845",
        "net_score": -45.25,
        "bullish_score": 80.48,
        "bearish_score": 122.21,
        "posts": 30,
        "change_pct": -0.95,
        "close": 18.61,
        "volume": 1024478.05
      },
      {
        "timestamp": "2025-10-04T04:45:24.793845",
        "net_score": -38.91,
        "bullish_score": 87.0,
        "bearish_score": 124.66,
        "posts": 30,
        "change_pct": 0.27,
        "close": 18.93,
        "volume": 846097.18
      },
      {
        "timestamp": "2025-10-04T05:45:24.793845",
        "net_score": -24.38,
        "bullish_score": 105.17,
        "bearish_score": 127.84,
        "posts": 35,
        "change_pct": 1.2,
        "close": 20.74,
        "volume": 1147007.34
      },
      {
        "timestamp": "2025-10-04T06:45:24.793845",
        "net_score": -40.29,
        "bullish_score": 94.26,
        "bearish_score": 125.22,
        "posts": 35,
        "change_pct": -0.02,
        "close": 21.37,
        "volume": 1243294.68
      },
      {
        "timestamp": "2025-10-04T07:45:24.793845",
        "net_score": -17.88,
        "bullish_score": 100.74,
        "bearish_score": 127.33,
        "posts": 25,
        "change_pct": 2.99,
        "close": 20.54,
        "volume": 889944.19
      },
      {
        "timestamp": "2025-10-04T08:45:24.793845",
        "net_score": -46.21,
        "bullish_score": 76.95,
        "bearish_score": 125.84,
        "posts": 35,
        "change_pct": 0.74,
        "close": 19.9,
        "volume": 731042.15
      },
      {
        "timestamp": "2025-10-04T09:45:24.793845",
        "net_score": -43.44,
        "bullish_score": 98.17,
        "bearish_score": 117.55,
        "posts": 35,
        "change_pct": 2.13,
        "close": 21.92,
        "volume": 1025910.12
      },
      {
        "timestamp": "2025-10-04T10:45:24.793845",
        "net_score": -14.25,
        "bullish_score": 92.45,
        "bearish_score": 125.17,
        "posts": 31,
        "change_pct": -0.2,
        "close": 20.48,
        "volume": 951480.74
      },
      {
        "timestamp": "2025-10-04T11:45:24.793845",
        "net_score": -16.7,
        "bullish_score": 93.37,
        "bearish_score": 134.58,
        "posts": 34,
        "change_pct": 2.36,
        "close": 21.52,
        "volume": 1276729.65
      },
      {
        "timestamp": "2025-10-04T12:45:24.793845",
        "net_score": -39.66,
        "bullish_score": 97.49,
        "bearish_score": 120.39,
        "posts": 28,
        "change_pct": -0.04,
        "close": 19.36,
        "volume": 784645.63
      },
      {
        "timestamp": "2025-10-04T13:45:24.793845",
        "net_score": -11.29,
        "bullish_score": 98.02,
        "bearish_score": 112.48,
        "posts": 34,
        "change_pct": 2.78,
        "close": 21.85,
        "volume": 1095317.47
      },
      {
        "timestamp": "2025-10-04T14:45:24.793845",
        "net_score": -48.99,
        "bullish_score": 97.0,
        "bearish_score": 113.52,
        "posts": 34,
        "change_pct": 2.13,
        "close": 18.99,
        "volume": 744276.68
      },
      {
        "timestamp": "2025-10-04T15:45:24.793845",
        "net_score": -39.97,
        "bullish_score": 94.52,
        "bearish_score": 116.53,
        "posts": 33,
        "change_pct": -2.33,
        "close": 19.22,
        "volume": 1267809.56
      },
      {
        "timestamp": "2025-10-04T16:45:24.793845",
        "net_score": -29.71,
        "bullish_score": 91.38,
        "bearish_score": 108.9,
        "posts": 32,
        "change_pct": -2.46,
        "close": 20.24,
        "volume": 1021743.54
      },
      {
        "timestamp": "2025-10-04T17:45:24.793845",
        "net_score": -16.6,
        "bullish_score": 98.82,
        "bearish_score": 115.31,
        "posts": 35,
        "change_pct": 0.3,
        "close": 18.05,
        "volume": 1241040.6
      },
      {
        "timestamp": "2025-10-04T18:45:24.793845",
        "net_score": -14.95,
        "bullish_score": 81.3,
        "bearish_score": 119.91,
        "posts": 28,
        "change_pct": -2.54,
        "close": 20.9,
        "volume": 849925.74
      },
      {
        "timestamp": "2025-10-04T19:45:24.793845",
        "net_score": -26.7,
        "bullish_score": 76.32,
        "bearish_score": 134.18,
        "posts": 35,
        "change_pct": -0.69,
        "close": 20.6,
        "volume": 1077876.13
      },
      {
        "timestamp": "2025-10-04T20:45:24.793845",
        "net_score": -16.98,
        "bullish_score": 82.04,
        "bearish_score": 129.71,
        "posts": 35,
        "change_pct": -1.75,
        "close": 18.73,
        "volume": 708844.04
      },
      {
        "timestamp": "2025-10-04T21:45:24.793845",
        "net_score": -26.16,
        "bullish_score": 93.33,
        "bearish_score": 125.93,
        "posts": 30,
        "change_pct": -0.26,
        "close": 20.05,
        "volume": 925155.65
      },
      {
        "timestamp": "2025-10-04T22:45:24.793845",
        "net_score": -40.03,
        "bullish_score": 78.2,
        "bearish_score": 131.17,
        "posts": 24,
        "change_pct": 0.95,
        "close": 19.56,
        "volume": 1114538.3
      },
      {
        "timestamp": "2025-10-04T23:55:31.516642+00:00",
        "net_score": -30.56,
        "bullish_score": 90.8,
        "bearish_score": 121.36,
        "posts": 30,
        "change_pct": null,
        "close": null,
        "volume": null
      },
      {
        "timestamp": "2025-10-06T18:42:26.177144+00:00",
        "net_score": -30.56,
        "bullish_score": 90.8,
        "bearish_score": 121.36,
        "posts": 30,
        "change_pct": null,
        "close": null,
        "volume": null
      }
    ]
  }
}